promptrefiner/__init__.py
promptrefiner/__main__.py
promptrefiner/base.py
promptrefiner/cli.py
promptrefiner/client_factory.py
promptrefiner/config.py
promptrefiner/refiner.py
promptrefiner/strategies/__init__.py
promptrefiner/strategies/chain_of_thought.py
promptrefiner/strategies/few_shot.py
promptrefiner/strategies/persona.py
promptrefiner/strategies/recursive_critique_refinement.py
promptrefiner/strategies/self_consistency.py
promptrefiner-1.0.0.dist-info/METADATA
promptrefiner-1.0.0.dist-info/WHEEL
promptrefiner-1.0.0.dist-info/entry_points.txt
promptrefiner-1.0.0.dist-info/licenses/LICENSE
promptrefiner-1.0.0.dist-info/RECORD
