Metadata-Version: 2.4
Name: promptrefiner
Version: 1.0.0
Summary: A Python library and CLI tool for refining prompts using various enhancement strategies.
Project-URL: Homepage, https://darshit7.github.io/promptrefiner/
Project-URL: Repository, https://github.com/darshit7/promptrefiner
Author-email: Darshit Patoliya <darshit7@gmail.com>
License: MIT License
License-File: LICENSE
Classifier: License :: OSI Approved :: MIT License
Classifier: Operating System :: OS Independent
Classifier: Programming Language :: Python :: 3
Requires-Python: >=3.9
Requires-Dist: litellm>=1.0.0
Requires-Dist: openai>=1.64.0
Requires-Dist: rich-click>=1.8.6
